custodium/__init__.py
custodium/exchange.py
custodium/portfolio.py
custodium/processing.py
custodium/reporting.py
custodium/utils.py
custodium-1.0.0.dist-info/licenses/LICENSE
custodium-1.0.0.dist-info/METADATA
custodium-1.0.0.dist-info/WHEEL
custodium-1.0.0.dist-info/top_level.txt
custodium-1.0.0.dist-info/RECORD
