Metadata-Version: 2.4
Name: custodium
Version: 1.0.0
Summary: A Python library for financial transaction processing and analysis.
Home-page: https://github.com/nsarang/custodium
Author: Nima Sarang
Author-email: contact@nimasarang.com
Project-URL: Homepage, https://github.com/nsarang/custodium
Project-URL: Issues, https://github.com/nsarang/custodium/issues
Project-URL: Documentation, https://github.com/nsarang/custodium#readme
Keywords: finance,transactions,portfolio,analysis,accounting
Classifier: Development Status :: 5 - Production/Stable
Classifier: Intended Audience :: Developers
Classifier: License :: OSI Approved :: MIT License
Classifier: Programming Language :: Python :: 3
Classifier: Programming Language :: Python :: 3.9
Classifier: Programming Language :: Python :: 3.10
Classifier: Programming Language :: Python :: 3.11
Classifier: Programming Language :: Python :: 3.12
Classifier: Programming Language :: Python :: 3.13
Classifier: Topic :: Software Development :: Debuggers
Requires-Python: >=3.8
License-File: LICENSE
Requires-Dist: pandas[output-formatting,plot]<=2.2.3,>=2.0.0
Requires-Dist: sortedcontainers<=2.4.0,>=2.2.0
Requires-Dist: requests<=2.32.3,>=2.24.0
Dynamic: author
Dynamic: author-email
Dynamic: classifier
Dynamic: description
Dynamic: description-content-type
Dynamic: home-page
Dynamic: keywords
Dynamic: license-file
Dynamic: project-url
Dynamic: requires-dist
Dynamic: requires-python
Dynamic: summary
